{
  "contact": {
    "name": "Mohammed Aslam Pasha",
    "email": "pashaaslam931@gmail.com",
    "location": "India"
  },
  "work_experience": [],
  "education": [
    {
      "institution": null,
      "degree": "Bachelor of Technology",
      "field_of_study": null,
      "start": null,
      "end": null
    }
  ],
  "skills": [
    {
      "name": "Java",
      "normalized_name": "java",
      "category": "Programming Languages"
    },
    {
      "name": "Spring Boot",
      "normalized_name": "spring boot",
      "category": "Programming Languages"
    },
    {
      "name": "MySQL",
      "normalized_name": "mysql",
      "category": "Databases"
    },
    {
      "name": "Git",
      "normalized_name": "git",
      "category": "DevOps & Containers"
    },
    {
      "name": "MVC",
      "normalized_name": "mvc",
      "category": "Methodologies"
    },
    {
      "name": "HTML",
      "normalized_name": "html",
      "category": "Programming Languages"
    },
    {
      "name": "CSS",
      "normalized_name": "css",
      "category": "Programming Languages"
    },
    {
      "name": "REST API",
      "normalized_name": "rest api",
      "category": "Programming Languages"
    },
    {
      "name": "Hibernate.",
      "normalized_name": "hibernate.",
      "category": "Project Tools"
    },
    {
      "name": "Bootstrap",
      "normalized_name": "bootstrap",
      "category": "Project Tools"
    },
    {
      "name": "JSP",
      "normalized_name": "jsp",
      "category": "Project Tools"
    },
    {
      "name": "JSTL.",
      "normalized_name": "jstl.",
      "category": "Project Tools"
    },
    {
      "name": "Joins",
      "normalized_name": "joins",
      "category": "Project Tools"
    },
    {
      "name": "Eclipse",
      "normalized_name": "eclipse",
      "category": "Project Tools"
    },
    {
      "name": "MySQL Workbench",
      "normalized_name": "mysql workbench",
      "category": "Project Tools"
    },
    {
      "name": "REST APIs.",
      "normalized_name": "rest apis.",
      "category": "Project Tools"
    }
  ],
  "certifications": [
    {
      "name": "performance. Certified Top Performer in Full Stack Development",
      "org": null
    },
    {
      "name": "6-Month Internship Certificate - QEdge Technologies",
      "org": null
    }
  ]
}