{
  "contact": {
    "name": "Advanced Indexing",
    "email": "j.sterling.dev@email.com",
    "location": "Charlotte, NC"
  },
  "work_experience": [
    {
      "title": "Server",
      "company": null,
      "start": "2016-01-01",
      "end": "2022-01-01",
      "current": false
    },
    {
      "title": "Frequency Transaction Engine Servicing Over 12 Million Global Users",
      "company": "Microservices Transformation (",
      "start": "2021-01-01",
      "end": "2022-01-01",
      "current": false
    },
    {
      "title": "Ensuring 100% Compliance With Hipaa Audits In 2018 And 2019",
      "company": null,
      "start": "2021-01-01",
      "end": null,
      "current": true
    },
    {
      "title": "Nc",
      "company": "Remote / Charlotte",
      "start": "2017-06-01",
      "end": "2020-12-01",
      "current": false
    },
    {
      "title": "Costs Via Efficiency Insights",
      "company": null,
      "start": "2014-05-01",
      "end": "2017-05-01",
      "current": false
    },
    {
      "title": "Ga",
      "company": "Atlanta",
      "start": "2018-01-01",
      "end": null,
      "current": true
    }
  ],
  "education": [
    {
      "institution": "Georgia Institute of Technology",
      "degree": "Bachelor of Science",
      "field_of_study": "Computer Science",
      "start": null,
      "end": null
    }
  ],
  "skills": [
    {
      "name": "SQL",
      "normalized_name": "sql",
      "category": "Databases"
    },
    {
      "name": ".NET",
      "normalized_name": ".net",
      "category": "Programming Languages"
    },
    {
      "name": "PostgreSQL",
      "normalized_name": "postgresql",
      "category": "Databases"
    },
    {
      "name": "MongoDB",
      "normalized_name": "mongodb",
      "category": "Databases"
    },
    {
      "name": "Azure",
      "normalized_name": "azure",
      "category": "Cloud Platforms"
    },
    {
      "name": "Docker",
      "normalized_name": "docker",
      "category": "DevOps & Containers"
    },
    {
      "name": "Kubernetes",
      "normalized_name": "kubernetes",
      "category": "DevOps & Containers"
    },
    {
      "name": "Terraform",
      "normalized_name": "terraform",
      "category": "DevOps & Containers"
    },
    {
      "name": "CI/CD",
      "normalized_name": "ci/cd",
      "category": "DevOps & Containers"
    },
    {
      "name": "Agile",
      "normalized_name": "agile",
      "category": "Methodologies"
    },
    {
      "name": "DevOps",
      "normalized_name": "devops",
      "category": "Methodologies"
    },
    {
      "name": "Communication",
      "normalized_name": "communication",
      "category": "Soft Skills"
    },
    {
      "name": "Leadership",
      "normalized_name": "leadership",
      "category": "Soft Skills"
    },
    {
      "name": "Testing",
      "normalized_name": "testing",
      "category": "Project Tools"
    },
    {
      "name": "RabbitMQ",
      "normalized_name": "rabbitmq",
      "category": "Big Data Technologies"
    },
    {
      "name": "Kafka",
      "normalized_name": "kafka",
      "category": "Big Data Technologies"
    },
    {
      "name": "NoSQL",
      "normalized_name": "nosql",
      "category": "Databases"
    },
    {
      "name": "Microservices",
      "normalized_name": "microservices",
      "category": "Methodologies"
    },
    {
      "name": "ORM",
      "normalized_name": "orm",
      "category": "Programming Languages"
    },
    {
      "name": "Cloud",
      "normalized_name": "cloud",
      "category": "Cloud Platforms"
    },
    {
      "name": "Backend",
      "normalized_name": "backend",
      "category": "Programming Languages"
    },
    {
      "name": "Security",
      "normalized_name": "security",
      "category": "Project Tools"
    },
    {
      "name": "VS Code",
      "normalized_name": "vs code",
      "category": "DevOps & Containers"
    },
    {
      "name": "SQL Server",
      "normalized_name": "sql server",
      "category": "Databases"
    },
    {
      "name": "REST API",
      "normalized_name": "rest api",
      "category": "Programming Languages"
    },
    {
      "name": "Cosmos DB",
      "normalized_name": "cosmos db",
      "category": "Databases"
    },
    {
      "name": "C#",
      "normalized_name": "c#",
      "category": "Programming Languages"
    },
    {
      "name": "MVC",
      "normalized_name": "mvc",
      "category": "Methodologies"
    },
    {
      "name": "Serverless",
      "normalized_name": "serverless",
      "category": "Project Tools"
    },
    {
      "name": "CQRS",
      "normalized_name": "cqrs",
      "category": "Project Tools"
    },
    {
      "name": "Hexagonal",
      "normalized_name": "hexagonal",
      "category": "Project Tools"
    },
    {
      "name": "LINQ",
      "normalized_name": "linq",
      "category": "Project Tools"
    },
    {
      "name": "Generics",
      "normalized_name": "generics",
      "category": "Project Tools"
    },
    {
      "name": "Reflection",
      "normalized_name": "reflection",
      "category": "Project Tools"
    },
    {
      "name": "Async",
      "normalized_name": "async",
      "category": "Project Tools"
    },
    {
      "name": "Await",
      "normalized_name": "await",
      "category": "Project Tools"
    },
    {
      "name": "Web API",
      "normalized_name": "web api",
      "category": "Project Tools"
    },
    {
      "name": "gRPC",
      "normalized_name": "grpc",
      "category": "Project Tools"
    },
    {
      "name": "SignalR.",
      "normalized_name": "signalr.",
      "category": "Project Tools"
    },
    {
      "name": "Relational",
      "normalized_name": "relational",
      "category": "Project Tools"
    },
    {
      "name": "Azure Cloud",
      "normalized_name": "azure cloud",
      "category": "Project Tools"
    },
    {
      "name": "PaaS",
      "normalized_name": "paas",
      "category": "Project Tools"
    },
    {
      "name": "IaaS",
      "normalized_name": "iaas",
      "category": "Project Tools"
    },
    {
      "name": "CI",
      "normalized_name": "ci",
      "category": "Project Tools"
    },
    {
      "name": "CD.",
      "normalized_name": "cd.",
      "category": "Project Tools"
    },
    {
      "name": "TDD",
      "normalized_name": "tdd",
      "category": "Project Tools"
    },
    {
      "name": "BDD",
      "normalized_name": "bdd",
      "category": "Project Tools"
    },
    {
      "name": "xUnit",
      "normalized_name": "xunit",
      "category": "Project Tools"
    },
    {
      "name": "Moq",
      "normalized_name": "moq",
      "category": "Project Tools"
    },
    {
      "name": "OAuth2",
      "normalized_name": "oauth2",
      "category": "Project Tools"
    },
    {
      "name": "HIPAA",
      "normalized_name": "hipaa",
      "category": "Project Tools"
    },
    {
      "name": "j.sterling.dev@email.com",
      "normalized_name": "j.sterling.dev@email.com",
      "category": "Project Tools"
    },
    {
      "name": "Frameworks",
      "normalized_name": "frameworks",
      "category": "Project Tools"
    },
    {
      "name": "Dapper",
      "normalized_name": "dapper",
      "category": "Project Tools"
    },
    {
      "name": "ADO.NET",
      "normalized_name": "ado.net",
      "category": "Project Tools"
    },
    {
      "name": "AutoMapper",
      "normalized_name": "automapper",
      "category": "Project Tools"
    },
    {
      "name": "FluentValidation.",
      "normalized_name": "fluentvalidation.",
      "category": "Project Tools"
    },
    {
      "name": "RESTful APIs",
      "normalized_name": "restful apis",
      "category": "Project Tools"
    },
    {
      "name": "HATEOAS",
      "normalized_name": "hateoas",
      "category": "Project Tools"
    },
    {
      "name": "Protobuf",
      "normalized_name": "protobuf",
      "category": "Project Tools"
    },
    {
      "name": "WebSockets",
      "normalized_name": "websockets",
      "category": "Project Tools"
    },
    {
      "name": "JetBrains Rider",
      "normalized_name": "jetbrains rider",
      "category": "Project Tools"
    },
    {
      "name": "LINQPad.",
      "normalized_name": "linqpad.",
      "category": "Project Tools"
    },
    {
      "name": "Postman",
      "normalized_name": "postman",
      "category": "Project Tools"
    },
    {
      "name": "SSMS",
      "normalized_name": "ssms",
      "category": "Project Tools"
    },
    {
      "name": "Azure Data Studio",
      "normalized_name": "azure data studio",
      "category": "Project Tools"
    },
    {
      "name": "MongoDB Compass",
      "normalized_name": "mongodb compass",
      "category": "Project Tools"
    },
    {
      "name": "GitKraken.",
      "normalized_name": "gitkraken.",
      "category": "Project Tools"
    }
  ],
  "certifications": [
    {
      "name": "Microsoft Certified: Azure Solutions Architect Expert",
      "org": "Microsoft"
    },
    {
      "name": "Microsoft Certified: Azure Developer Associate (AZ-204)",
      "org": "Microsoft"
    },
    {
      "name": "AWS Certified Developer - Associate",
      "org": "Amazon Web Services"
    },
    {
      "name": "Certified ScrumMaster (CSM) - Scrum Alliance",
      "org": null
    },
    {
      "name": "HashiCorp Certified: Terraform Associate",
      "org": null
    }
  ]
}